{
  "generated_at": "2026-07-23T18:19:23.620383-04:00",
  "event_key": "2026-07-23|La Suerte|Quiniela La Suerte 6PM",
  "target": {
    "time_rd": "2026-07-23 19:00",
    "lottery": "La Primera",
    "draw": "Quiniela La Primera Noche"
  },
  "best_play": {
    "time_rd": "2026-07-23 19:00",
    "lottery": "La Primera",
    "draw": "Quiniela La Primera Noche",
    "top12": [
      "65",
      "90",
      "48",
      "97",
      "35",
      "06",
      "26",
      "86",
      "50",
      "42",
      "00",
      "92"
    ],
    "topq": [
      "65",
      "90",
      "48"
    ],
    "pales": [
      "65-90",
      "48-65",
      "65-97"
    ],
    "fingerprint": "566888816899786f",
    "ok_alert": false,
    "decision": "❌ NO JUGAR",
    "best_signal": 0.02942622972175507,
    "best_a11": 2,
    "debug": {
      "best_signal_hist": 0.02942622972175507,
      "best_a11_hist": 2,
      "today_observed_nums": 20,
      "source_pairs_today": 7,
      "source_rows_hist_used": 2400,
      "top12_overlap_prev": 2,
      "top_intraday": [
        [
          "67",
          2
        ],
        [
          "65",
          1
        ],
        [
          "69",
          1
        ],
        [
          "21",
          1
        ],
        [
          "43",
          1
        ]
      ]
    }
  }
}