{
  "generated_at": "2026-03-31T19:19:55.514257-04:00",
  "event_key": "2026-03-31|TEST|NO-UPDATE",
  "target": {
    "time_rd": "2026-03-31 21:00",
    "lottery": "La Nacional",
    "draw": "Loteria Nacional- Noche"
  },
  "best_play": {
    "time_rd": "2026-03-31 21:00",
    "lottery": "La Nacional",
    "draw": "Loteria Nacional- Noche",
    "top12": [
      "38",
      "85",
      "84",
      "35",
      "13",
      "21",
      "04",
      "39",
      "29",
      "92",
      "61",
      "72"
    ],
    "topq": [
      "38",
      "85",
      "84"
    ],
    "pales": [
      "38-85",
      "38-84",
      "35-38"
    ],
    "fingerprint": "2a71bde9ce394c1e",
    "ok_alert": false,
    "best_signal": 0.016844075048733132,
    "best_a11": 3,
    "debug": {
      "best_signal_hist": 0.016844075048733132,
      "best_a11_hist": 3,
      "today_observed_nums": 20,
      "source_pairs_today": 8,
      "source_rows_hist_used": 2600,
      "top12_overlap_prev": 1,
      "top_intraday": [
        [
          "10",
          2
        ],
        [
          "16",
          1
        ],
        [
          "55",
          1
        ],
        [
          "36",
          1
        ],
        [
          "01",
          1
        ]
      ]
    }
  }
}