{
  "generated_at": "2026-04-24T09:15:03.220150-04:00",
  "event_key": "2026-04-24|TEST|NO-UPDATE",
  "target": {
    "time_rd": "2026-04-24 10:00",
    "lottery": "Anguilla",
    "draw": "Anguila 10AM"
  },
  "best_play": {
    "time_rd": "2026-04-24 10:00",
    "lottery": "Anguilla",
    "draw": "Anguila 10AM",
    "top12": [
      "34",
      "64",
      "37",
      "76",
      "69",
      "74",
      "83",
      "48",
      "02",
      "39",
      "08",
      "15"
    ],
    "topq": [
      "34",
      "64",
      "37"
    ],
    "pales": [
      "34-64",
      "34-37",
      "34-76"
    ],
    "fingerprint": "cd20630094c69348",
    "ok_alert": false,
    "decision": "❌ NO JUGAR",
    "best_signal": 0.04418396451929684,
    "best_a11": 3,
    "debug": {
      "best_signal_hist": 0.04418396451929684,
      "best_a11_hist": 3,
      "today_observed_nums": 0,
      "source_pairs_today": 0,
      "source_rows_hist_used": 3540,
      "top12_overlap_prev": 0,
      "top_intraday": []
    }
  }
}