{
  "generated_at": "2026-05-01T14:06:16.734633-04:00",
  "event_key": "2026-05-01|Anguilla|Anguila 1PM",
  "items": [
    {
      "generated_at": "2026-05-01T14:06:16.278835-04:00",
      "event_key": "2026-05-01|Anguilla|Anguila 1PM",
      "target": {
        "time_rd": "2026-05-01 14:30",
        "lottery": "La Nacional",
        "draw": "Loteria Nacional- Gana Más"
      },
      "best_play": {
        "time_rd": "2026-05-01 14:30",
        "lottery": "La Nacional",
        "draw": "Loteria Nacional- Gana Más",
        "top12": [
          "33",
          "78",
          "25",
          "73",
          "94",
          "91",
          "13",
          "96",
          "44",
          "20",
          "23",
          "80"
        ],
        "topq": [
          "33",
          "78",
          "25"
        ],
        "pales": [
          "33-78",
          "25-33",
          "33-73"
        ],
        "fingerprint": "f0da1e66f9ba0757",
        "ok_alert": false,
        "decision": "❌ NO JUGAR",
        "best_signal": 0.01873875851487426,
        "best_a11": 3,
        "debug": {
          "best_signal_hist": 0.01873875851487426,
          "best_a11_hist": 3,
          "today_observed_nums": 11,
          "source_pairs_today": 4,
          "source_rows_hist_used": 2148,
          "top12_overlap_prev": 0,
          "top_intraday": [
            [
              "47",
              2
            ],
            [
              "79",
              1
            ],
            [
              "50",
              1
            ],
            [
              "53",
              1
            ],
            [
              "33",
              1
            ]
          ]
        }
      }
    }
  ]
}