{
  "generated_at": "2026-05-03T13:14:18.910051-04:00",
  "event_key": "2026-05-03|Anguilla|Anguila 1PM",
  "target": {
    "time_rd": "2026-05-03 14:30",
    "lottery": "La Nacional",
    "draw": "Loteria Nacional- Gana Más"
  },
  "best_play": {
    "time_rd": "2026-05-03 14:30",
    "lottery": "La Nacional",
    "draw": "Loteria Nacional- Gana Más",
    "top12": [
      "44",
      "25",
      "73",
      "33",
      "94",
      "91",
      "13",
      "90",
      "96",
      "20",
      "23",
      "65"
    ],
    "topq": [
      "44",
      "25",
      "73"
    ],
    "pales": [
      "25-44",
      "44-73",
      "33-44"
    ],
    "fingerprint": "44c2c3dbfdd1b949",
    "ok_alert": false,
    "decision": "❌ NO JUGAR",
    "best_signal": 0.01873875851487426,
    "best_a11": 3,
    "debug": {
      "best_signal_hist": 0.01873875851487426,
      "best_a11_hist": 3,
      "today_observed_nums": 11,
      "source_pairs_today": 4,
      "source_rows_hist_used": 2148,
      "top12_overlap_prev": 0,
      "top_intraday": [
        [
          "89",
          2
        ],
        [
          "56",
          1
        ],
        [
          "35",
          1
        ],
        [
          "49",
          1
        ],
        [
          "44",
          1
        ]
      ]
    }
  }
}