{
  "generated_at": "2026-06-13T11:33:43.220711-04:00",
  "event_key": "2026-06-13|TEST|NO-UPDATE",
  "items": [
    {
      "generated_at": "2026-06-13T11:33:42.487087-04:00",
      "event_key": "2026-06-13|TEST|NO-UPDATE",
      "target": {
        "time_rd": "2026-06-13 12:00",
        "lottery": "La Primera",
        "draw": "Quiniela La Primera"
      },
      "best_play": {
        "time_rd": "2026-06-13 12:00",
        "lottery": "La Primera",
        "draw": "Quiniela La Primera",
        "top12": [
          "92",
          "76",
          "26",
          "08",
          "24",
          "58",
          "90",
          "03",
          "23",
          "72",
          "47",
          "59"
        ],
        "topq": [
          "92",
          "76",
          "26"
        ],
        "pales": [
          "76-92",
          "26-92",
          "08-92"
        ],
        "fingerprint": "657d1367e3367529",
        "ok_alert": false,
        "decision": "❌ NO JUGAR",
        "best_signal": 0.01574439463173827,
        "best_a11": 2,
        "debug": {
          "best_signal_hist": 0.01574439463173827,
          "best_a11_hist": 2,
          "today_observed_nums": 3,
          "source_pairs_today": 1,
          "source_rows_hist_used": 528,
          "top12_overlap_prev": 3,
          "top_intraday": [
            [
              "36",
              1
            ],
            [
              "92",
              1
            ],
            [
              "29",
              1
            ]
          ]
        }
      }
    }
  ]
}