{
  "generated_at": "2026-06-01T13:58:09.089539-04:00",
  "event_key": "2026-06-01|Anguilla|Anguila 1PM",
  "items": [
    {
      "generated_at": "2026-06-01T13:56:59.868501-04:00",
      "event_key": "2026-06-01|Anguilla|Anguila 1PM",
      "target": {
        "time_rd": "2026-06-01 14:30",
        "lottery": "La Nacional",
        "draw": "Loteria Nacional- Gana Más"
      },
      "best_play": {
        "time_rd": "2026-06-01 14:30",
        "lottery": "La Nacional",
        "draw": "Loteria Nacional- Gana Más",
        "top12": [
          "13",
          "60",
          "53",
          "41",
          "95",
          "20",
          "64",
          "40",
          "94",
          "37",
          "89",
          "63"
        ],
        "topq": [
          "13",
          "60",
          "53"
        ],
        "pales": [
          "13-60",
          "13-53",
          "13-41"
        ],
        "fingerprint": "08900c02a1b5549c",
        "ok_alert": false,
        "decision": "❌ NO JUGAR",
        "best_signal": 0.0013941099749780917,
        "best_a11": 5,
        "debug": {
          "best_signal_hist": 0.0013941099749780917,
          "best_a11_hist": 5,
          "today_observed_nums": 12,
          "source_pairs_today": 4,
          "source_rows_hist_used": 1554,
          "top12_overlap_prev": 2,
          "top_intraday": [
            [
              "47",
              1
            ],
            [
              "13",
              1
            ],
            [
              "11",
              1
            ],
            [
              "65",
              1
            ],
            [
              "17",
              1
            ]
          ]
        }
      }
    }
  ]
}