{
  "generated_at": "2026-07-16T10:33:59.004353-04:00",
  "event_key": "2026-07-16|TEST|NO-UPDATE",
  "items": [
    {
      "generated_at": "2026-07-16T10:33:58.242657-04:00",
      "event_key": "2026-07-16|TEST|NO-UPDATE",
      "target": {
        "time_rd": "2026-07-16 12:00",
        "lottery": "La Primera",
        "draw": "Quiniela La Primera"
      },
      "best_play": {
        "time_rd": "2026-07-16 12:00",
        "lottery": "La Primera",
        "draw": "Quiniela La Primera",
        "top12": [
          "38",
          "09",
          "24",
          "29",
          "03",
          "90",
          "76",
          "23",
          "92",
          "58",
          "59",
          "69"
        ],
        "topq": [
          "38",
          "09",
          "24"
        ],
        "pales": [
          "09-38",
          "24-38",
          "29-38"
        ],
        "fingerprint": "cf79eee3178ef6f3",
        "ok_alert": false,
        "decision": "❌ NO JUGAR",
        "best_signal": 0.017313438735077225,
        "best_a11": 2,
        "debug": {
          "best_signal_hist": 0.017313438735077225,
          "best_a11_hist": 2,
          "today_observed_nums": 0,
          "source_pairs_today": 1,
          "source_rows_hist_used": 531,
          "top12_overlap_prev": 1,
          "top_intraday": []
        }
      }
    }
  ]
}