{
  "generated_at": "2026-07-17T19:20:40.635403-04:00",
  "event_key": "2026-07-17|La Primera|Quiniela La Primera Noche",
  "items": [
    {
      "generated_at": "2026-07-17T19:20:01.987685-04:00",
      "event_key": "2026-07-17|La Primera|Quiniela La Primera Noche",
      "target": {
        "time_rd": "2026-07-17 21:00",
        "lottery": "Anguilla",
        "draw": "Anguila 9PM"
      },
      "best_play": {
        "time_rd": "2026-07-17 21:00",
        "lottery": "Anguilla",
        "draw": "Anguila 9PM",
        "top12": [
          "63",
          "44",
          "43",
          "94",
          "12",
          "46",
          "59",
          "48",
          "84",
          "19",
          "51",
          "58"
        ],
        "topq": [
          "63",
          "44",
          "43"
        ],
        "pales": [
          "44-63",
          "43-63",
          "63-94"
        ],
        "fingerprint": "5ac0bcd811abf6a7",
        "ok_alert": false,
        "decision": "❌ NO JUGAR",
        "best_signal": 0.029022166434593804,
        "best_a11": 3,
        "debug": {
          "best_signal_hist": 0.029022166434593804,
          "best_a11_hist": 3,
          "today_observed_nums": 21,
          "source_pairs_today": 8,
          "source_rows_hist_used": 2400,
          "top12_overlap_prev": 0,
          "top_intraday": [
            [
              "99",
              3
            ],
            [
              "62",
              2
            ],
            [
              "82",
              1
            ],
            [
              "50",
              1
            ],
            [
              "63",
              1
            ]
          ]
        }
      }
    },
    {
      "generated_at": "2026-07-17T19:20:39.912939-04:00",
      "event_key": "2026-07-17|La Primera|Quiniela La Primera Noche",
      "target": {
        "time_rd": "2026-07-17 21:00",
        "lottery": "La Nacional",
        "draw": "Loteria Nacional- Noche"
      },
      "best_play": {
        "time_rd": "2026-07-17 21:00",
        "lottery": "La Nacional",
        "draw": "Loteria Nacional- Noche",
        "top12": [
          "56",
          "76",
          "47",
          "55",
          "60",
          "67",
          "65",
          "33",
          "94",
          "84",
          "57",
          "39"
        ],
        "topq": [
          "56",
          "76",
          "47"
        ],
        "pales": [
          "56-76",
          "47-56",
          "55-56"
        ],
        "fingerprint": "8d4bf17854580ce6",
        "ok_alert": false,
        "decision": "❌ NO JUGAR",
        "best_signal": 0.03312099254456703,
        "best_a11": 3,
        "debug": {
          "best_signal_hist": 0.03312099254456703,
          "best_a11_hist": 3,
          "today_observed_nums": 21,
          "source_pairs_today": 8,
          "source_rows_hist_used": 2400,
          "top12_overlap_prev": 2,
          "top_intraday": [
            [
              "99",
              3
            ],
            [
              "62",
              2
            ],
            [
              "82",
              1
            ],
            [
              "50",
              1
            ],
            [
              "63",
              1
            ]
          ]
        }
      }
    }
  ]
}