{
  "generated_at": "2026-04-16T12:45:43.884045-04:00",
  "event_key": "2026-04-16|La Suerte|Quiniela La Suerte",
  "target": {
    "time_rd": "2026-04-16 13:00",
    "lottery": "Anguilla",
    "draw": "Anguila 1PM"
  },
  "best_play": {
    "time_rd": "2026-04-16 13:00",
    "lottery": "Anguilla",
    "draw": "Anguila 1PM",
    "top12": [
      "73",
      "96",
      "11",
      "62",
      "52",
      "21",
      "68",
      "43",
      "87",
      "69",
      "60",
      "02"
    ],
    "topq": [
      "73",
      "96",
      "11"
    ],
    "pales": [
      "73-96",
      "11-73",
      "62-73"
    ],
    "fingerprint": "0b47bc3511f719dc",
    "ok_alert": false,
    "decision": "❌ NO JUGAR",
    "best_signal": 0.01539654752813477,
    "best_a11": 2,
    "debug": {
      "best_signal_hist": 0.01539654752813477,
      "best_a11_hist": 2,
      "today_observed_nums": 9,
      "source_pairs_today": 3,
      "source_rows_hist_used": 1614,
      "top12_overlap_prev": 1,
      "top_intraday": [
        [
          "50",
          1
        ],
        [
          "26",
          1
        ],
        [
          "83",
          1
        ],
        [
          "43",
          1
        ],
        [
          "36",
          1
        ]
      ]
    }
  }
}